<FSData version="9.0"><Airport name="Grand Canyon Natl Park" ident="KGCN" lat="35.952361151576" lon="-112.146972119808" alt="0.0"><Ils lat="35.9638074785471" lon="-112.134866416454" alt="2014.423M" heading="40.5800018310547" frequency="108.900" range="50017.0M" magvar="-10.28" ident="IGCN" width="4" name="ILS/DME 03"><GlideSlope lat="35.9456888213754" lon="-112.155480533838" alt="2014.423M" pitch="3" range="50017.0M" /><Dme lat="35.9638054668903" lon="-112.134863734245" alt="2014.423M" range="50017.0M" /></Ils><Waypoint lat="35.8799529075623" lon="-112.22334176302" waypointType="NAMED" magvar="-10.3" waypointRegion="K2" waypointIdent="HAPLY" /><Waypoint lat="35.8744835481048" lon="-112.209430485964" waypointType="UNNAMED" magvar="-10.29" waypointRegion="K2" waypointIdent="FF03" /><Waypoint lat="35.9141668304801" lon="-112.34333306551" waypointType="NAMED" magvar="-10.34" waypointRegion="K2" waypointIdent="RURIW" /><Waypoint lat="35.9048917517066" lon="-112.382708340883" waypointType="NAMED" magvar="-10.35" waypointRegion="K2" waypointIdent="AMERE" /><Waypoint lat="35.828797146678" lon="-112.331683337688" waypointType="UNNAMED" magvar="-10.32" waypointRegion="K2" waypointIdent="D214L" /><Waypoint lat="35.8053030073643" lon="-112.301891595125" waypointType="NAMED" magvar="-10.31" waypointRegion="K2" waypointIdent="CARMS" /><Waypoint lat="35.6959667801857" lon="-112.416544407606" waypointType="NAMED" magvar="-10.33" waypointRegion="K2" waypointIdent="SAVRE" /></Airport><Airport name="Valle" ident="40G" lat="35.6506471708417" lon="-112.148044556379" alt="0.0"><Waypoint lat="35.7961000129581" lon="-112.079230695963" waypointType="NAMED" magvar="-10.24" waypointRegion="K2" waypointIdent="JAVPU" /><Waypoint lat="35.4894112050533" lon="-112.224041819572" waypointType="NAMED" magvar="-10.23" waypointRegion="K2" waypointIdent="JUDDU" /><Waypoint lat="35.6565584242344" lon="-112.145536243916" waypointType="UNNAMED" magvar="-10.24" waypointRegion="K2" waypointIdent="MA19" /><Waypoint lat="35.6451835110784" lon="-112.150633335114" waypointType="NAMED" magvar="-10.24" waypointRegion="K2" waypointIdent="UGBOY" /><Waypoint lat="35.4290249571204" lon="-112.126380801201" waypointType="NAMED" magvar="-10.19" waypointRegion="K2" waypointIdent="JATID" /><Waypoint lat="35.5673028901219" lon="-112.187371999025" waypointType="NAMED" magvar="-10.24" waypointRegion="K2" waypointIdent="IVLEC" /><Waypoint lat="35.8234749734402" lon="-112.14582234621" waypointType="UNNAMED" magvar="-10.26" waypointRegion="K2" waypointIdent="GCN08" /><Waypoint lat="35.7266556099057" lon="-112.145655602217" waypointType="NAMED" magvar="-10.25" waypointRegion="K2" waypointIdent="GUCNO" /><Waypoint lat="35.793430544436" lon="-112.1457695961" waypointType="UNNAMED" magvar="-10.26" waypointRegion="K2" waypointIdent="CF19" /><Waypoint lat="35.8116695657372" lon="-112.071847468615" waypointType="NAMED" magvar="-10.24" waypointRegion="K2" waypointIdent="EHGUY" /><Waypoint lat="35.5193362757564" lon="-112.319322377443" waypointType="NAMED" magvar="-10.27" waypointRegion="K2" waypointIdent="CAJLA" /><Waypoint lat="35.7338140904903" lon="-112.108733206987" waypointType="NAMED" magvar="-10.24" waypointRegion="K2" waypointIdent="VALEQ" /></Airport><Airport name="Window Rock" ident="KRQE" lat="35.6520556658506" lon="-109.067388921976" alt="0.0"><Waypoint lat="35.5893141031265" lon="-108.993275016546" waypointType="NAMED" magvar="-9.09" waypointRegion="K2" waypointIdent="RANOY" /><Waypoint lat="35.6530722230673" lon="-109.061377644539" waypointType="NAMED" magvar="-9.13" waypointRegion="K2" waypointIdent="ZUBOD" /><Waypoint lat="35.5749388039112" lon="-109.131169617176" waypointType="NAMED" magvar="-9.14" waypointRegion="K2" waypointIdent="CONPO" /><Waypoint lat="35.4919056594372" lon="-109.199677705765" waypointType="NAMED" magvar="-9.16" waypointRegion="K2" waypointIdent="HABON" /><Waypoint lat="35.5777417123318" lon="-109.105097204447" waypointType="NAMED" magvar="-9.13" waypointRegion="K2" waypointIdent="NUNCA" /><Waypoint lat="35.8548333495855" lon="-109.043839126825" waypointType="NAMED" magvar="-9.15" waypointRegion="K2" waypointIdent="WUDID" /><Waypoint lat="35.6331584975123" lon="-109.083024859428" waypointType="NAMED" magvar="-9.13" waypointRegion="K2" waypointIdent="SUNEE" /><Waypoint lat="35.7549361512065" lon="-109.052536189556" waypointType="NAMED" magvar="-9.14" waypointRegion="K2" waypointIdent="ROCLO" /><Waypoint lat="35.6102168932557" lon="-109.102008193731" waypointType="NAMED" magvar="-9.14" waypointRegion="K2" waypointIdent="POMBE" /></Airport><Airport name="Gallup Mun" ident="KGUP" lat="35.5110583081841" lon="-108.789308220148" alt="0.0"><Ils lat="35.5146038532257" lon="-108.774297684431" alt="1972.665M" heading="73.8399963378906" frequency="111.700" range="50017.0M" magvar="-8.99" ident="IGUP" width="5.48999977111816" name="LOC/DME 06"><Dme lat="35.5146028473973" lon="-108.774297237396" alt="1972.665M" range="50017.0M" /></Ils><Waypoint lat="35.4792416095734" lon="-108.923639059067" waypointType="NAMED" magvar="-9.05" waypointRegion="K2" waypointIdent="HUMGI" /><Waypoint lat="35.4846419021487" lon="-108.900897055864" waypointType="NAMED" magvar="-9.04" waypointRegion="K2" waypointIdent="KINLY" /><Waypoint lat="35.5138444527984" lon="-108.777514100075" waypointType="NAMED" magvar="-8.99" waypointRegion="K2" waypointIdent="QASSY" /><Waypoint lat="35.4511112719774" lon="-109.026166945696" waypointType="NAMED" magvar="-9.08" waypointRegion="K2" waypointIdent="ZUPRA" /><Waypoint lat="35.4759944602847" lon="-108.872614055872" waypointType="NAMED" magvar="-9.03" waypointRegion="K2" waypointIdent="ADABY" /><Waypoint lat="35.3234780207276" lon="-108.955455422401" waypointType="NAMED" magvar="-9.04" waypointRegion="K2" waypointIdent="ARABE" /><Waypoint lat="35.3949417918921" lon="-109.050908088684" waypointType="NAMED" magvar="-9.09" waypointRegion="K2" waypointIdent="BERSE" /><Waypoint lat="35.4725082591176" lon="-108.950833529234" waypointType="UNNAMED" magvar="-9.06" waypointRegion="K2" waypointIdent="CF06" /><Waypoint lat="35.4950029402971" lon="-108.857185989618" waypointType="NAMED" magvar="-9.02" waypointRegion="K2" waypointIdent="CIBDI" /><Waypoint lat="35.5281446501613" lon="-108.716880530119" waypointType="NAMED" magvar="-8.97" waypointRegion="K2" waypointIdent="DEYEB" /><Waypoint lat="35.654030777514" lon="-108.550441414118" waypointType="NAMED" magvar="-8.92" waypointRegion="K2" waypointIdent="EKIYO" /><Waypoint lat="35.545547157526" lon="-108.642894476652" waypointType="NAMED" magvar="-8.95" waypointRegion="K2" waypointIdent="FESIX" /><Waypoint lat="35.5737918242812" lon="-108.522325158119" waypointType="NAMED" magvar="-8.9" waypointRegion="K2" waypointIdent="BAXTU" /></Airport><Airport name="Love" ident="KPRC" lat="34.6544723957777" lon="-112.41958335042" alt="0.0"><Ils lat="34.6443822607398" lon="-112.43021607399" alt="1537.716M" heading="221.199996948242" frequency="108.500" range="50017.0M" magvar="-10.16" ident="IPRC" width="4.88000011444092" name="ILS/DME 21L"><GlideSlope lat="34.6589332446456" lon="-112.41329446435" alt="1537.716M" pitch="3" range="50017.0M" /><Dme lat="34.6443805843592" lon="-112.430213838816" alt="1537.716M" range="50017.0M" /></Ils><Waypoint lat="34.8284501954913" lon="-112.613144516945" waypointType="NAMED" magvar="-10.25" waypointRegion="K2" waypointIdent="DILLY" /><Waypoint lat="34.7738360613585" lon="-112.56713077426" waypointType="NAMED" magvar="-10.23" waypointRegion="K2" waypointIdent="OKAPY" /><Waypoint lat="34.7111528366804" lon="-112.682141661644" waypointType="UNNAMED" magvar="-10.25" waypointRegion="K2" waypointIdent="D259J" /><Waypoint lat="34.7724973037839" lon="-112.293874919415" waypointType="NAMED" magvar="-10.14" waypointRegion="K2" waypointIdent="RUBIW" /><Waypoint lat="34.842966645956" lon="-112.447725087404" waypointType="NAMED" magvar="-10.2" waypointRegion="K2" waypointIdent="PUROO" /><Waypoint lat="34.8801668733358" lon="-112.178844362497" waypointType="NAMED" magvar="-10.12" waypointRegion="K2" waypointIdent="PEVYU" /><Waypoint lat="34.661341868341" lon="-112.412200123072" waypointType="NAMED" magvar="-10.16" waypointRegion="K2" waypointIdent="OXANE" /><Waypoint lat="34.5797668397427" lon="-112.49876126647" waypointType="NAMED" magvar="-10.17" waypointRegion="K2" waypointIdent="AJDUX" /><Waypoint lat="34.8249777406454" lon="-112.102877944708" waypointType="NAMED" magvar="-10.09" waypointRegion="K2" waypointIdent="AKUHY" /><Waypoint lat="34.7710888087749" lon="-112.295383214951" waypointType="UNNAMED" magvar="-10.14" waypointRegion="K2" waypointIdent="CF21L" /><Waypoint lat="34.869297221303" lon="-112.469649910927" waypointType="UNNAMED" magvar="-10.21" waypointRegion="K2" waypointIdent="D349J" /><Waypoint lat="34.9353529885411" lon="-112.254863977432" waypointType="NAMED" magvar="-10.15" waypointRegion="K2" waypointIdent="DUKIW" /><Waypoint lat="34.7246611118317" lon="-112.345663905144" waypointType="NAMED" magvar="-10.15" waypointRegion="K2" waypointIdent="HOPKY" /><Waypoint lat="34.7347723692656" lon="-112.334083467722" waypointType="NAMED" magvar="-10.15" waypointRegion="K2" waypointIdent="HUMTY" /><Waypoint lat="34.7953778877854" lon="-112.292963862419" waypointType="NAMED" magvar="-10.14" waypointRegion="K2" waypointIdent="JAWXY" /><Waypoint lat="34.6483556181192" lon="-112.426002770662" waypointType="NAMED" magvar="-10.16" waypointRegion="K2" waypointIdent="JURAX" /><Waypoint lat="34.7240529209375" lon="-112.345499843359" waypointType="NAMED" magvar="-10.15" waypointRegion="K2" waypointIdent="LUGQO" /><Waypoint lat="34.6533777192235" lon="-112.42863625288" waypointType="UNNAMED" magvar="-10.16" waypointRegion="K2" waypointIdent="MA12" /><Waypoint lat="34.7133083269" lon="-112.497497051954" waypointType="NAMED" magvar="-10.2" waypointRegion="K2" waypointIdent="MULHU" /><Waypoint lat="34.8243138939142" lon="-112.322241514921" waypointType="NAMED" magvar="-10.16" waypointRegion="K2" waypointIdent="MUNNS" /></Airport><Airport name="Sedona" ident="KSEZ" lat="34.8486277833581" lon="-111.788461357355" alt="0.0"><Waypoint lat="34.8285554721951" lon="-111.81345552206" waypointType="NAMED" magvar="-9.99" waypointRegion="K2" waypointIdent="LOMBB" /><Waypoint lat="34.7154752165079" lon="-111.953927725554" waypointType="NAMED" magvar="-10.02" waypointRegion="K2" waypointIdent="EXUTY" /><Waypoint lat="34.655744433403" lon="-111.883339136839" waypointType="NAMED" magvar="-9.99" waypointRegion="K2" waypointIdent="BOWSU" /></Airport><Airport name="Flagstaff Pulliam" ident="KFLG" lat="35.1384555548429" lon="-111.671219319105" alt="0.0"><Ils lat="35.1379278302193" lon="-111.673358380795" alt="2136.952M" heading="224" frequency="110.500" range="50017.0M" magvar="-9.99" ident="IFLG" width="4" name="ILS 21"><GlideSlope lat="35.1440861821175" lon="-111.665916591883" alt="2136.952M" pitch="3" range="50017.0M" /></Ils><Waypoint lat="35.1921278983355" lon="-111.57905548811" waypointType="NAMED" magvar="-9.97" waypointRegion="K2" waypointIdent="ZIGNO" /><Waypoint lat="35.1965002343059" lon="-111.567972153425" waypointType="UNNAMED" magvar="-9.97" waypointRegion="K2" waypointIdent="FQ21" /><Waypoint lat="35.2918500825763" lon="-111.491047292948" waypointType="UNNAMED" magvar="-9.96" waypointRegion="K2" waypointIdent="CF21" /><Waypoint lat="35.2699555456638" lon="-111.429774910212" waypointType="UNNAMED" magvar="-9.93" waypointRegion="K2" waypointIdent="PUU14" /><Waypoint lat="35.2419056743383" lon="-111.482508480549" waypointType="UNNAMED" magvar="-9.95" waypointRegion="K2" waypointIdent="CQ21" /><Waypoint lat="35.2098304778337" lon="-111.463919430971" waypointType="NAMED" magvar="-9.94" waypointRegion="K2" waypointIdent="SHEFF" /><Waypoint lat="35.2319918945432" lon="-111.561944335699" waypointType="NAMED" magvar="-9.97" waypointRegion="K2" waypointIdent="SHUTR" /><Waypoint lat="35.1814111322165" lon="-111.559522300959" waypointType="UNNAMED" magvar="-9.96" waypointRegion="K2" waypointIdent="FF21" /><Waypoint lat="35.2190277725458" lon="-111.482788771391" waypointType="NAMED" magvar="-9.94" waypointRegion="K2" waypointIdent="UMARE" /><Waypoint lat="35.0055028125644" lon="-111.812502890825" waypointType="NAMED" magvar="-10.02" waypointRegion="K2" waypointIdent="SEZCY" /><Waypoint lat="35.1505583524704" lon="-111.654249876738" waypointType="UNNAMED" magvar="-9.99" waypointRegion="K2" waypointIdent="MQ21" /><Waypoint lat="35.1529166847467" lon="-111.655061244965" waypointType="UNNAMED" magvar="-9.99" waypointRegion="K2" waypointIdent="MA21" /><Waypoint lat="35.1456888020039" lon="-111.663516461849" waypointType="NAMED" magvar="-9.99" waypointRegion="K2" waypointIdent="INUZE" /><Waypoint lat="35.107005648315" lon="-111.609266549349" waypointType="UNNAMED" magvar="-9.97" waypointRegion="K2" waypointIdent="FF293" /><Waypoint lat="35.0935057550669" lon="-111.719022095203" waypointType="UNNAMED" magvar="-10.0" waypointRegion="K2" waypointIdent="30THR" /><Waypoint lat="35.0683610513806" lon="-111.745736002922" waypointType="NAMED" magvar="-10.01" waypointRegion="K2" waypointIdent="TOHQU" /><Waypoint lat="35.1184724271297" lon="-111.37135013938" waypointType="NAMED" magvar="-9.89" waypointRegion="K2" waypointIdent="TAWNE" /></Airport><Airport name="Winslow-Lindbergh Regl" ident="KINW" lat="35.021916590631" lon="-110.722527801991" alt="0.0"><Waypoint lat="35.123986043036" lon="-110.983419567347" waypointType="NAMED" magvar="-9.76" waypointRegion="K2" waypointIdent="DMJCH" /><Waypoint lat="34.915547221899" lon="-110.893274992704" waypointType="NAMED" magvar="-9.7" waypointRegion="K2" waypointIdent="IZSAH" /></Airport><Airport name="Payson" ident="KPAN" lat="34.2568362504244" lon="-111.339255720377" alt="0.0"><Waypoint lat="34.2545027285814" lon="-111.339444369078" waypointType="NAMED" magvar="-9.75" waypointRegion="K2" waypointIdent="EVODE" /><Waypoint lat="34.1735610365868" lon="-111.346261203289" waypointType="NAMED" magvar="-9.74" waypointRegion="K2" waypointIdent="MINAM" /><Waypoint lat="34.0736279636621" lon="-111.354680657387" waypointType="NAMED" magvar="-9.72" waypointRegion="K2" waypointIdent="OPUMY" /><Waypoint lat="34.0518749132752" lon="-111.185283511877" waypointType="NAMED" magvar="-9.66" waypointRegion="K2" waypointIdent="TOPEE" /></Airport><Airport name="St Johns Industrial" ident="KSJN" lat="34.5185554772615" lon="-109.378750026226" alt="0.0"><Waypoint lat="34.5127250254154" lon="-109.373844265938" waypointType="NAMED" magvar="-9.09" waypointRegion="K2" waypointIdent="MARPD" /><Waypoint lat="34.4733723253012" lon="-109.271427690983" waypointType="NAMED" magvar="-9.04" waypointRegion="K2" waypointIdent="PAFEL" /><Waypoint lat="34.4511750340462" lon="-109.048238843679" waypointType="NAMED" magvar="-8.96" waypointRegion="K2" waypointIdent="IZZOM" /><Waypoint lat="34.3913835659623" lon="-109.236213862896" waypointType="NAMED" magvar="-9.02" waypointRegion="K2" waypointIdent="DMYVN" /></Airport><Airport name="Black Rock" ident="KZUN" lat="35.0832278653979" lon="-108.791777640581" alt="0.0"><Waypoint lat="34.9657528102398" lon="-109.154511094093" waypointType="NAMED" magvar="-9.07" waypointRegion="K2" waypointIdent="JIXCO" /><Waypoint lat="35.081216879189" lon="-108.799444288015" waypointType="NAMED" magvar="-8.95" waypointRegion="K2" waypointIdent="OJEXY" /><Waypoint lat="35.0863499566913" lon="-108.802274912596" waypointType="UNNAMED" magvar="-8.95" waypointRegion="K2" waypointIdent="MA06" /><Waypoint lat="35.0302250683308" lon="-108.992752879858" waypointType="NAMED" magvar="-9.01" waypointRegion="K2" waypointIdent="NEZCO" /><Waypoint lat="35.055758357048" lon="-108.896127641201" waypointType="NAMED" magvar="-8.98" waypointRegion="K2" waypointIdent="DOFFY" /><Waypoint lat="35.0556584447622" lon="-108.892305493355" waypointType="UNNAMED" magvar="-8.98" waypointRegion="K2" waypointIdent="FF06" /></Airport><Airport name="Show Low Regl" ident="KSOW" lat="34.2654722929001" lon="-110.00566676259" alt="0.0"><Waypoint lat="34.3198805674911" lon="-109.958666861057" waypointType="NAMED" magvar="-9.28" waypointRegion="K2" waypointIdent="AHPAZ" /><Waypoint lat="34.2900084704161" lon="-109.89207521081" waypointType="NAMED" magvar="-9.25" waypointRegion="K2" waypointIdent="CUBOL" /><Waypoint lat="34.3330223858356" lon="-109.94625851512" waypointType="UNNAMED" magvar="-9.27" waypointRegion="K2" waypointIdent="FF205" /><Waypoint lat="34.3123723939061" lon="-109.783424735069" waypointType="NAMED" magvar="-9.21" waypointRegion="K2" waypointIdent="JASUR" /><Waypoint lat="34.260461255908" lon="-110.034836232662" waypointType="NAMED" magvar="-9.3" waypointRegion="K2" waypointIdent="ZAXIN" /><Waypoint lat="34.3323860317469" lon="-109.6857444942" waypointType="NAMED" magvar="-9.18" waypointRegion="K2" waypointIdent="WESUM" /></Airport><Airport name="Taylor Mun" ident="KTYL" lat="34.4528416916728" lon="-110.114825069904" alt="0.0"><Waypoint lat="34.53109446913" lon="-109.898372143507" waypointType="NAMED" magvar="-9.29" waypointRegion="K2" waypointIdent="DPAUL" /><Waypoint lat="34.5232084393501" lon="-110.040686130524" waypointType="NAMED" magvar="-9.34" waypointRegion="K2" waypointIdent="BOLYN" /><Waypoint lat="34.5860666781664" lon="-109.974300116301" waypointType="NAMED" magvar="-9.32" waypointRegion="K2" waypointIdent="CAMBA" /><Waypoint lat="34.640994630754" lon="-110.050325095654" waypointType="NAMED" magvar="-9.36" waypointRegion="K2" waypointIdent="BANZO" /></Airport><Airport name="Town Of Springerville Mun" ident="D68" lat="34.1354444995523" lon="-109.310025125742" alt="0.0"><Waypoint lat="34.1664665937424" lon="-109.28311675787" waypointType="UNNAMED" magvar="-9.01" waypointRegion="K2" waypointIdent="19THR" /><Waypoint lat="34.1386722028255" lon="-109.30150821805" waypointType="NAMED" magvar="-9.01" waypointRegion="K2" waypointIdent="EXMAP" /><Waypoint lat="34.2849250137806" lon="-109.2045776546" waypointType="NAMED" magvar="-8.99" waypointRegion="K2" waypointIdent="IFADE" /><Waypoint lat="34.2118083313107" lon="-109.253086298704" waypointType="NAMED" magvar="-9.0" waypointRegion="K2" waypointIdent="IWEDU" /></Airport></FSData>