<FSData version="9.0"><Airport name="Vagar" ident="EKVG" lat="62.0636276900768" lon="-7.27721929550171" alt="0.0"><Ils lat="62.0685193687677" lon="-7.28042766451836" alt="85.344M" heading="104" frequency="109.100" range="50017.0M" magvar="3.95" ident="SF" width="5" name="LOC/DME 13"><Dme lat="62.0685193687677" lon="-7.28042766451836" alt="85.344M" range="50017.0M" /></Ils><Ils lat="62.0649915933609" lon="-7.28536382317543" alt="85.344M" heading="296" frequency="110.300" range="50017.0M" magvar="3.95" ident="MF" width="5" name="LOC/DME 31"><Dme lat="62.0649915933609" lon="-7.28536382317543" alt="85.344M" range="50017.0M" /></Ils><Waypoint lat="61.9445084407926" lon="-6.76518872380257" waypointType="UNNAMED" magvar="3.67" waypointRegion="EK" waypointIdent="D126P" /><Waypoint lat="61.984416693449" lon="-6.93609416484833" waypointType="UNNAMED" magvar="3.76" waypointRegion="EK" waypointIdent="CL31" /><Waypoint lat="61.969669573009" lon="-6.87278866767883" waypointType="UNNAMED" magvar="3.73" waypointRegion="EK" waypointIdent="D126M" /><Waypoint lat="61.9597333297133" lon="-6.83021932840347" waypointType="UNNAMED" magvar="3.71" waypointRegion="EK" waypointIdent="D126N" /><Waypoint lat="62.0431027561426" lon="-7.18992501497269" waypointType="UNNAMED" magvar="3.9" waypointRegion="EK" waypointIdent="ML31" /><Waypoint lat="62.0813416689634" lon="-7.39046663045883" waypointType="UNNAMED" magvar="4.01" waypointRegion="EK" waypointIdent="FL13" /><Waypoint lat="62.0020723342896" lon="-7.01214149594307" waypointType="UNNAMED" magvar="3.8" waypointRegion="EK" waypointIdent="FL31" /><Waypoint lat="62.0753415673971" lon="-7.33887478709221" waypointType="UNNAMED" magvar="3.98" waypointRegion="EK" waypointIdent="ML13" /><Waypoint lat="61.8483418598771" lon="-6.63098886609077" waypointType="UNNAMED" magvar="3.59" waypointRegion="EK" waypointIdent="AB27" /></Airport></FSData>