<FSData version="9.0"><Airport name="Nadzab" ident="AYNZ" lat="-6.56983327120543" lon="146.72624990344" alt="0.0"><Waypoint lat="-6.64447210729122" lon="146.89500823617" waypointType="UNNAMED" magvar="-5.24" waypointRegion="AY" waypointIdent="CF27" /><Waypoint lat="-6.56248603016138" lon="146.625425219536" waypointType="UNNAMED" magvar="-5.16" waypointRegion="AY" waypointIdent="FF09" /><Waypoint lat="-6.57601945102215" lon="146.819022148848" waypointType="UNNAMED" magvar="-5.21" waypointRegion="AY" waypointIdent="FF27" /><Waypoint lat="-6.56020011752844" lon="146.592847108841" waypointType="UNNAMED" magvar="-5.15" waypointRegion="AY" waypointIdent="FS09" /><Waypoint lat="-6.54721654951572" lon="146.408266872168" waypointType="NAMED" magvar="-5.1" waypointRegion="AY" waypointIdent="WEST" /><Waypoint lat="-6.5566223859787" lon="146.541899889708" waypointType="UNNAMED" magvar="-5.13" waypointRegion="AY" waypointIdent="CF09" /></Airport></FSData>